nova_act_mcp/__init__.py
nova_act_mcp/__main__.py
nova_act_mcp/server.py
nova_act_mcp-0.2.1.dist-info/METADATA
nova_act_mcp-0.2.1.dist-info/WHEEL
nova_act_mcp-0.2.1.dist-info/entry_points.txt
nova_act_mcp-0.2.1.dist-info/licenses/LICENSE
nova_act_mcp-0.2.1.dist-info/licenses/NOTICE.html
nova_act_mcp-0.2.1.dist-info/RECORD
